chainless/__init__.py
chainless/logger.py
chainless/_schemas/__init__.py
chainless/_utils/__init__.py
chainless/_utils/_serialization.py
chainless/_utils/_utility.py
chainless/_utils/_validate_callback.py
chainless/_utils/_validate_name.py
chainless/core/Agent.py
chainless/core/TaskFlow.py
chainless/core/Tool.py
chainless/core/taskflow/__init__.py
chainless/core/taskflow/task_context.py
chainless/core/taskflow/task_executor.py
chainless/interfaces/AgentProtocol.py
chainless/interfaces/__init__.py
chainless-0.1.1.dist-info/METADATA
chainless-0.1.1.dist-info/WHEEL
chainless-0.1.1.dist-info/licenses/LICENSE.txt
chainless-0.1.1.dist-info/RECORD
