Metadata-Version: 2.4
Name: chainless
Version: 0.1.1
Summary: Chainless is a lightweight, modular framework to build task-oriented AI agents and orchestrate them in intelligent flows
Author-email: Onur Artan <onur@roticeh.com>
License-File: LICENSE.txt
Requires-Python: >=3.10
Requires-Dist: httpx>=0.28.1
Requires-Dist: langchain-core>=0.3.58
Requires-Dist: langchain>=0.3.25
Requires-Dist: networkx>=3.4.2
Requires-Dist: pydantic>=2.11.4
Requires-Dist: python-dotenv>=1.1.0
Requires-Dist: rich>=14.0.0
Requires-Dist: tenacity>=9.1.2
